[
    {
        "title": "ergqergqer",
        "text": "qergqergaegaerg",
        "note_id": "84435656-2d50-458c-a9b6-90b962f8ed30"
    },
    {
        "title": "dgsgsdg",
        "text": "ertewrtertewhrthrthrth",
        "note_id": "1d7e6f38-4e1d-40d1-9d74-667cf04e9c15"
    },
    {
        "title": "eweqwetert",
        "text": "ereqryeryeryereve",
        "note_id": "39bac0c0-caea-4f30-96a2-bae8f19534dd"
    },
    {
        "title": "trtrtjwrj",
        "text": "wrtjwrtjtyjtyjteyjtyj",
        "note_id": "78dc4e84-dab1-4393-b47e-a5dac82a09b5"
    }
]